banner_nish/__init__.py
banner_nish/banner.py
banner_nish-1.1.2.dist-info/METADATA
banner_nish-1.1.2.dist-info/WHEEL
banner_nish-1.1.2.dist-info/entry_points.txt
banner_nish-1.1.2.dist-info/top_level.txt
banner_nish-1.1.2.dist-info/RECORD
