Metadata-Version: 2.1
Name: banner_nish
Version: 1.1.2
Summary: Banner Output for Python
Author-email: NishNovae <raecrowned@gmail.com>
License: MIT
Project-URL: Homepage, https://github.com/NishNovae/banner_nish
Project-URL: Issues, https://github.com/NishNovae/banner_nish/issues
Requires-Python: >=3.9
Requires-Dist: pyfiglet >=1.0.2
